pydecompress/__init__.py
pydecompress/extractor.py
pydecompress-0.0.2.dist-info/METADATA
pydecompress-0.0.2.dist-info/WHEEL
pydecompress-0.0.2.dist-info/top_level.txt
pydecompress-0.0.2.dist-info/RECORD
