Metadata-Version: 2.1
Name: pydecompress
Version: 0.0.2
Summary: PyDecompress eases the process of extracting contents from different types of archives.
Home-page: https://github.com/polkovnik-z/pydecompress
Author: Ibragim Abubakarov
Author-email: ibragim.ai95@gmail.com
Maintainer: Ibragim Abubakarov
Maintainer-email: ibragim.ai95@gmail.com
License: UNKNOWN
Platform: UNKNOWN
Classifier: Programming Language :: Python :: 3
Classifier: Operating System :: OS Independent
Classifier: Intended Audience :: Developers
